cc_nbdev_template/__init__.py
cc_nbdev_template/_nbdev.py
cc_nbdev_template/core.py
ccnbdev_template/__init__.py
ccnbdev_template/_nbdev.py
ccnbdev_template/core.py
nbdev_template/__init__.py
nbdev_template/_nbdev.py
nbdev_template/core.py
cc_nbdev_template-0.0.2.dist-info/LICENSE
cc_nbdev_template-0.0.2.dist-info/METADATA
cc_nbdev_template-0.0.2.dist-info/WHEEL
cc_nbdev_template-0.0.2.dist-info/entry_points.txt
cc_nbdev_template-0.0.2.dist-info/top_level.txt
cc_nbdev_template-0.0.2.dist-info/RECORD
